Workbook

Sheet Check List
B3: CREDIT INITIATION UNIT – (STAGE 1) –APPROVAL SHEET FOR Mortgage LOAN
B4: Amendment Date 10 Sep 2018 | H4: App ID : _______________________ | K4: =INPUT!#REF! -> #ERROR!
B5: Applicant Name : | D5: =INPUT!#REF! -> #ERROR!
B6: Originating Branch/Unit | D6: Direct Sales / Branch Name | K6: Branch Code:
B7: *JS ACCOUNT HOLDER | E7: Yes | F7: No A/c No : | H7: =INPUT!#REF! -> #ERROR! | I7: Account Opening Date :
B12: Self Employed | F12: Salaried | J12: ECIB
J13: eCIB:
B14: £ CNIC / NICOP | F14: £ CNIC / NICOP | J14: £ No History
B15: £ 02 recent photos | F15: £ 02 recent photos | J15: £ Clean History
B16: £ Property Title Docs | F16: £ Property Title Docs | J16: £ 30 DPD
B17: £ Legal Advice | F17: £ Legal Advice | J17: £ 60 DPD
B18: £ Appraiser Report | F18: £ Appraiser Report | J18: £ 90 or 90+ DPD
B19: £ Verification Report | F19: £ Verification Report | J19: £ Write off , amount _______
B20: £ Proof of business | F20: £ Salary slip
B21: £ 06 Month B/S | F21: £ 06 Month B/S | J21: CMs Age : ___________
B22: £ Verysis | F22: £ Verysis | J22: Co-Borrower:
B23: £ Data Check | F23: £ Data Check | J23: Relation : _________________
B25: __________________________________________ | J25: Gross Income(p.m) : ________
C26: £ | E26: Buy your Ghar:
B27: Build your Ghar: | C27: £ | E27: Build your Ghar: | J27: Cross Product Check :
B28: Renovate your Ghar: | C28: £ | E28: Renovate your Ghar | J28: £ Credit Card
B29: Balance Transfer: | C29: £ | E29: Balance Transfer: | J29: £ Auto Loan
B30: Build and Buy Ghar: | C30: £ | E30: Build and Buy Ghar: | J30: ETB – NTB – NTI
D32: £ | E32: Apartment
D33: £ | E33: Plot
D34: £ | E34: House
H35: Risk Analysis
B36: Rate + KIBOR | F36: Floating / Fixed : 1 Year KIBOR + | K36: = | N36: %
B37: Equity Percentage | F37: =INPUT!#REF! -> #ERROR!
B38: Appraised Value
H39: =INPUT!#REF! -> #ERROR!
B41: Laon Applied
B42: Laon Tenor
B43: Income / Average Balance
B45: FSV
F46: =INPUT!#REF! -> #ERROR!
B47: LTV
B48: DBR% | F48: ='DBR Sheet'!B28 -> #DIV/0!
B49: Application Score | F49: ='DBR Sheet'!#REF! -> #ERROR!
H50: CIU Comments (If Any)
B54: CP CHECKED______________ | E54: FRMU CHECKED DATED ____________________ | K54: OFFER LETTER DATED_____________
B55: Deviation | C55: Yes | D55: No | E55: Reason For Stage 1 Deviation_______________________________
B56: Deviation Type | D56: Level 1(GH-CRBG) | H56: K+4.25% /, Equity
B57: (Maximum 3 per | D57: Level 2 (CPM or BH/Head of Product) | K57: Deviation
B58: case otherwise | D58: Level 3 (CIU Head) | K58: Approval
B59: Exception)
H60: Risk Approval
B61: CIU Approval & Date: | H61: Exception Yes No
H62: Recommended by GH – CRGB
H63: Approved by : President & CEO
B64: Risk Approval & Date:

Sheet INPUT
B1: Credit Cards DBR |Calculator - Inputs | Z1: Subhan Z. Ghanvi
B2: User Name | C2: kodev.ali@jsbl.com | L2: =TODAY() -> 46051
U3: =Formulas!B9 -> #N/A
B4: Customer Information | F4: Segments | L4: Income Calculations | M4: =Formulas!E15 -> #N/A
B5: App ID | F5: Company Category | J5: Emp. Banking | L5: Fixed Income
B6: Name | F6: Employement Type | L6: =IF(H10=1,"Estimated Income","Bank Stmt Income") -> Bank Stmt Income
B7: CNIC | F7: Deviation (If any) | L7: Variable Income
B8: Date Of Birth | F8: Prime Tagging | L8: Total Income
B9: Age | D9: =IF(AND(U3="Self Employed",C9<18),"Below Age",IF(AND(U3<>"Self Employed",C9<21),"Below Age",IF(AND(U3="Self Employed",C9>70),"Above Age",IF(AND(U3<>"Self Employed",C9>70),"Above Age","")))) -> #N/A | F9: Target Market | L9: Deductiona
F10: Bureau | J10: Muliples | L10: Net Income
E11: 1 | F11: Allowable Limit As Per Policy | H11: =Formulas!J28 -> #N/A | J11: =Formulas!I7 -> #N/A
B12: E - CIB Inputs | F12: Assigned Limit | J12: =CONCATENATE('DBR Sheet'!C28,'DBR Sheet'!G11) -> #DIV/0!
L14: =IF(COUNTIF(O16:O36,"Fin. Date >Mat, Date")>0,"Fin. Date >Mat, Date","")
B15: If Manual Installment Select (Yes) | C15: Product | D15: Term / EverGreen | E15: LIMIT | F15: Position as of | G15: Present Balance | H15: Minimum Amount Due | I15: 30+ | J15: 60+ | K15: 90+ | L15: Financing Date | M15: Maturity Date | N15: Sec / Un Sec | O15: Date check | P15: Manual Installment
O22: =IF(L22>M22,"Fin. Date >Mat, Date","")
O23: =IF(L23>M23,"Fin. Date >Mat, Date","")
O24: =IF(L24>M24,"Fin. Date >Mat, Date","")
O25: =IF(L25>M25,"Fin. Date >Mat, Date","")
O26: =IF(L26>M26,"Fin. Date >Mat, Date","")
O27: =IF(L27>M27,"Fin. Date >Mat, Date","")
O28: =IF(L28>M28,"Fin. Date >Mat, Date","")
O29: =IF(L29>M29,"Fin. Date >Mat, Date","")
O30: =IF(L30>M30,"Fin. Date >Mat, Date","")
O31: =IF(L31>M31,"Fin. Date >Mat, Date","")
O32: =IF(L32>M32,"Fin. Date >Mat, Date","")
O33: =IF(L33>M33,"Fin. Date >Mat, Date","")
... O36: =IF(L36>M36,"Fin. Date >Mat, Date","")

Sheet DBR Sheet
A2: =CONCATENATE("MCE Generatd by", " ",INPUT!C2," ","on", " ",TEXT(NOW(),"[$-F800]dddd, mmmm dd, yyyy")) -> MCE Generatd by kodev.ali@jsbl.com on Thursday, January 29, 2026 | E2: * Version Vx21.3.0 - Limit Exposure Check| 12-October-2021
A3: Personal Information
A4: App ID | B4: =INPUT!C5 | E4: Ecib - EMI
A5: Customer Name | B5: =INPUT!C6 | E5: Total EMI of All Products | F5: =SUM(H34:H65)+F26 -> 0
A6: CNIC | B6: =INPUT!C7 | E6: Total Market EMI Exc. JS Card | F6: =SUM(H34:H65) -> 0
A7: Age of Applicant | B7: =INPUT!C9 | C7: =INPUT!C8 | D7: =INPUT!D9 -> #N/A | E7: Total EMI of Unsecured. Exc. JS Card | F7: =SUMIFS($H$34:$H$65,$R$34:$R$65,"U") -> 0
A8: Company Category | B8: =Formulas!B9 -> #N/A | E8: Total EMI of Secured Products | F8: =SUMIFS($H$34:$H$65,$R$34:$R$65,"S") -> 0
A9: Employment Category | B9: =IF(B8="Self Employed",B8,Formulas!D7) -> #N/A
A10: 0 | B10: =INPUT!K5 | E10: Ecib - Exposures
A11: Prime | B11: =Formulas!I5 -> #N/A | E11: Total Un-Secured Exposure. Availed | G11: =IF(AND(B11="Yes",F11>7000000),"Unsec Exp Exceeds 7mm",IF(AND(F11>3000000,B11<>"Yes"),"Unsec Exp Exceeds 3mm","")) -> #N/A | K11: =3000000-F12 -> 3000000
A12: ECIB | B12: =Formulas!C13 -> NTI | E12: Total Market Unsecured Exp Exc. JS Card | F12: =F11-F24 -> 0 | K12: =7000000-F12 -> 7000000
A13: Deviation | B13: =Formulas!F8 -> #N/A | E13: Ramaining Un-secured Exposure | F13: =IF(B11="No",K11,K12)*0.95 -> #N/A
A15: Income Estimation | E15: Application Score
A16: Gross Income | B16: =INPUT!M5 | C16: =INPUT!M4 -> #N/A
A17: Variable Income | B17: =INPUT!M7
A18: Total Income | B18: =B16+B17 -> 0 | C18: =IF(B17<>0,"Variable income considered","")
A19: Total Deductions | B19: =INPUT!M9
A20: Net Income | B20: =B18-B19 -> 0
A23: P | E23: Actual | F23: Actual with EOL
A24: Recommended Exposure | B24: =INPUT!H11 -> #N/A | D24: Exposure
A25: Approved Limit
B26: =INPUT!H13 | D26: EMI | E26: =B25*0.05 -> 0 | F26: =(B25+E26)*0.05 -> 0
A28: Current Debt Burden | B28: =F5/B20 -> #DIV/0! | C28: =IF(B28>=39.5%,"HIGH DBR",IF(B28>0.35,"B.H Recommendation Required.",IF(B28<=0.35,""))) -> #DIV/0!
A29: DB Allowed | B29: =IF(C28="B.H Recommendation Required.",35%,40%) -> #DIV/0!
O30: =IF(B34="E",0.05*C34,IF(AND(OR(A34=9,A34=33,A34=46),B34="T"),PMT(0.15/12,J34,-C34),IF(AND(OR(A34=29,A34=24,A34=25,A34=26,A34=27,A34=28),B34="T"),PMT(0.18/12,J34,-C34),IF(AND(OR(A34=6,A34=15,A34=16,A34=17,A34=21,A34=31),B34="T"),PMT(0.2/12,J34,-C34),IF(AND(A34=4,B34="T"),PMT(0.21/12,J34,-C34),IF(AND(OR(A34=37,A34=38),B34="T"),PMT(0.26/12,J34,-C34),IF(AND(A34=54,B34="T"),PMT(0.05/12,J34,-C34),0))))))) -> 0
A31: MDB PART
C32: oldest product (for Credit History (MDB)) | E32: =MIN(E34:E65) -> 0 | J32: oldest product Unsecured | L32: =MIN(L34:L65) -> 0 | M32: =MIN(M34:M65) -> 0 | N32: oldest product Secured | AC32: NEW | AD32: NEW
A33: Product | B33: T / E | C33: Limit | D33: Present Balance | E33: F / Date (Pls Don’t Leave Blank) | F33: M/R Date (Pls Don't Leave Blank) | G33: Sec / Unsec ( must be filled ) | H33: Installment | I33: Rates | J33: Tenor (mths) | K33: Tenor (mths) crnt date | L33: Unsecured Dates | M33: Secured Dates | N33: Un-Secured Exposure | O33: Installment | P33: a | Q33: Secured Exposure | S33: Key | X33: 0 | Y33: 0 | Z33: NR | AC33: Exposure | AD33: cc chheck
A34: =IF(INPUT!C16="","",INPUT!C16) | B34: =IF(INPUT!D16="","",INPUT!D16) | C34: =IF(INPUT!E16="","",INPUT!E16) | D34: =IF(INPUT!G16="","",INPUT!G16) | E34: =IF(INPUT!L16="","",INPUT!L16) | F34: =IF(INPUT!M16="","",INPUT!M16) | G34: =IF(H34="","",CONCATENATE(IF(INPUT!N16="","",INPUT!N16)," - ",TEXT(H34,"0,00"))) | H34: =IF(A34="","",IF(P34="y",INPUT!P16,O34)) | I34: =IFERROR(VLOOKUP(S34,Formulas!$T$2:$U$77,2,0),"") | J34: =IF(F34="",0,(F34-E34)/(365.25/12)) -> 0 | K34: =IF(E34="",0,(TODAY()-E34)/(365.25/12)) -> 0 | L34: =IF(AND(R34="U",NOT(E34="")),E34,"") | M34: =IF(AND(R34="S",NOT(E34="")),E34,"") | N34: =IF(AND(OR(A34=38,A34=54,A34=5,A34=8),R34="U"),C34,"") | O34: =IFERROR(IF(B34="E",(C34*0.05)+AD34,PMT(VLOOKUP(S34,Formulas!T:U,2,0)/12,J34,-C34)),0) -> 0 | P34: =INPUT!B16 | Q34: =IF(AND(OR(A34=38,A34=54,A34=5,A34=8),R34="S"),C34,"") | R34: =INPUT!N16 | S34: =A34&"-"&B34&"-"&R34 -> -- | U34: count | V34: =COUNT(A34:A65) -> 0 | X34: 0 | Y34: 6 | Z34: NTI | AC34: =IF(AND(B34="E",R34="U",D34>C34),D34,IF(AND(B34="E",R34="U",D34<=C34),C34,IF(AND(B34="T",R34="U"),D34,IF(AND(B34="E",R34="S",D34>C34),D34,IF(AND(B34="T",R34="S"),D34,0))))) -> 0 | AD34: =IF(B34<>"E",0,IF(D34-C34<0,0,D34-C34)) -> 0
A35: =IF(INPUT!C17="","",INPUT!C17) | B35: =IF(INPUT!D17="","",INPUT!D17) | C35: =IF(INPUT!E17="","",INPUT!E17) | D35: =IF(INPUT!G17="","",INPUT!G17) | E35: =IF(INPUT!L17="","",INPUT!L17) | F35: =IF(INPUT!M17="","",INPUT!M17) | G35: =IF(H35="","",CONCATENATE(IF(INPUT!N17="","",INPUT!N17)," - ",TEXT(H35,"0,00"))) | H35: =IF(A35="","",IF(P35="y",INPUT!P17,O35)) | I35: =IFERROR(VLOOKUP(S35,Formulas!$T$2:$U$77,2,0),"") | J35: =IF(F35="",0,(F35-E35)/(365.25/12)) -> 0 | K35: =IF(E35="",0,(TODAY()-E35)/(365.25/12)) -> 0 | L35: =IF(AND(R35="U",NOT(E35="")),E35,"") | M35: =IF(AND(R35="S",NOT(E35="")),E35,"") | N35: =IF(AND(OR(A35=38,A35=54,A35=5,A35=8),R35="U"),C35,"") | O35: =IFERROR(IF(B35="E",(C35*0.05)+AD35,PMT(VLOOKUP(S35,Formulas!T:U,2,0)/12,J35,-C35)),0) -> 0 | P35: =INPUT!B17 | Q35: =IF(AND(OR(A35=38,A35=54,A35=5,A35=8),R35="S"),C35,"") | R35: =INPUT!N17 | S35: =A35&"-"&B35&"-"&R35 -> -- | V35: =IF(V34>6,"6+",V34) -> 0 | X35: 7 | Y35: 11 | Z35: NTB | AC35: =IF(AND(B35="E",R35="U",D35>C35),D35,IF(AND(B35="E",R35="U",D35<=C35),C35,IF(AND(B35="T",R35="U"),D35,IF(AND(B35="E",R35="S",D35>C35),D35,IF(AND(B35="T",R35="S"),D35,0))))) -> 0 | AD35: =IF(B35<>"E",0,IF(D35-C35<0,0,D35-C35)) -> 0
A36: =IF(INPUT!C18="","",INPUT!C18) | B36: =IF(INPUT!D18="","",INPUT!D18) | C36: =IF(INPUT!E18="","",INPUT!E18) | D36: =IF(INPUT!G18="","",INPUT!G18) | E36: =IF(INPUT!L18="","",INPUT!L18) | F36: =IF(INPUT!M18="","",INPUT!M18) | G36: =IF(H36="","",CONCATENATE(IF(INPUT!N18="","",INPUT!N18)," - ",TEXT(H36,"0,00"))) | H36: =IF(A36="","",IF(P36="y",INPUT!P18,O36)) | I36: =IFERROR(VLOOKUP(S36,Formulas!$T$2:$U$77,2,0),"") | J36: =IF(F36="",0,(F36-E36)/(365.25/12)) -> 0 | K36: =IF(E36="",0,(TODAY()-E36)/(365.25/12)) -> 0 | L36: =IF(AND(R36="U",NOT(E36="")),E36,"") | M36: =IF(AND(R36="S",NOT(E36="")),E36,"") | N36: =IF(AND(OR(A36=38,A36=54,A36=5,A36=8),R36="U"),C36,"") | O36: =IFERROR(IF(B36="E",(C36*0.05)+AD36,PMT(VLOOKUP(S36,Formulas!T:U,2,0)/12,J36,-C36)),0) -> 0 | P36: =INPUT!B18 | Q36: =IF(AND(OR(A36=38,A36=54,A36=5,A36=8),R36="S"),C36,"") | R36: =INPUT!N18 | S36: =A36&"-"&B36&"-"&R36 -> -- | V36: =MAX(K34:K65) -> 0 | X36: 12 | Y36: 1000 | Z36: ETB | AC36: =IF(AND(B36="E",R36="U",D36>C36),D36,IF(AND(B36="E",R36="U",D36<=C36),C36,IF(AND(B36="T",R36="U"),D36,IF(AND(B36="E",R36="S",D36>C36),D36,IF(AND(B36="T",R36="S"),D36,0))))) -> 0 | AD36: =IF(B36<>"E",0,IF(D36-C36<0,0,D36-C36)) -> 0
A37: =IF(INPUT!C19="","",INPUT!C19) | B37: =IF(INPUT!D19="","",INPUT!D19) | C37: =IF(INPUT!E19="","",INPUT!E19) | D37: =IF(INPUT!G19="","",INPUT!G19) | E37: =IF(INPUT!L19="","",INPUT!L19) | F37: =IF(INPUT!M19="","",INPUT!M19) | G37: =IF(H37="","",CONCATENATE(IF(INPUT!N19="","",INPUT!N19)," - ",TEXT(H37,"0,00"))) | H37: =IF(A37="","",IF(P37="y",INPUT!P19,O37)) | I37: =IFERROR(VLOOKUP(S37,Formulas!$T$2:$U$77,2,0),"") | J37: =IF(F37="",0,(F37-E37)/(365.25/12)) -> 0 | K37: =IF(E37="",0,(TODAY()-E37)/(365.25/12)) -> 0 | L37: =IF(AND(R37="U",NOT(E37="")),E37,"") | M37: =IF(AND(R37="S",NOT(E37="")),E37,"") | N37: =IF(AND(OR(A37=38,A37=54,A37=5,A37=8),R37="U"),C37,"") | O37: =IFERROR(IF(B37="E",(C37*0.05)+AD37,PMT(VLOOKUP(S37,Formulas!T:U,2,0)/12,J37,-C37)),0) -> 0 | P37: =INPUT!B19 | Q37: =IF(AND(OR(A37=38,A37=54,A37=5,A37=8),R37="S"),C37,"") | R37: =INPUT!N19 | S37: =A37&"-"&B37&"-"&R37 -> -- | V37: =LOOKUP(V36,$X$33:$Y$36,$Z$33:$Z$36) -> NTI | AC37: =IF(AND(B37="E",R37="U",D37>C37),D37,IF(AND(B37="E",R37="U",D37<=C37),C37,IF(AND(B37="T",R37="U"),D37,IF(AND(B37="E",R37="S",D37>C37),D37,IF(AND(B37="T",R37="S"),D37,0))))) -> 0 | AD37: =IF(B37<>"E",0,IF(D37-C37<0,0,D37-C37)) -> 0
A38: =IF(INPUT!C20="","",INPUT!C20) | B38: =IF(INPUT!D20="","",INPUT!D20) | C38: =IF(INPUT!E20="","",INPUT!E20) | D38: =IF(INPUT!G20="","",INPUT!G20) | F38: =IF(INPUT!M20="","",INPUT!M20) | G38: =IF(H38="","",CONCATENATE(IF(INPUT!N20="","",INPUT!N20)," - ",TEXT(H38,"0,00"))) | H38: =IF(A38="","",IF(P38="y",INPUT!P20,O38)) | I38: =IFERROR(VLOOKUP(S38,Formulas!$T$2:$U$77,2,0),"") | J38: =IF(F38="",0,(F38-E38)/(365.25/12)) -> 0 | K38: =IF(E38="",0,(TODAY()-E38)/(365.25/12)) -> 0 | L38: =IF(AND(R38="U",NOT(E38="")),E38,"") | M38: =IF(AND(R38="S",NOT(E38="")),E38,"") | N38: =IF(AND(OR(A38=38,A38=54,A38=5,A38=8),R38="U"),C38,"") | O38: =IFERROR(IF(B38="E",(C38*0.05)+AD38,PMT(VLOOKUP(S38,Formulas!T:U,2,0)/12,J38,-C38)),0) -> 0 | P38: =INPUT!B20 | Q38: =IF(AND(OR(A38=38,A38=54,A38=5,A38=8),R38="S"),C38,"") | R38: =INPUT!N20 | S38: =A38&"-"&B38&"-"&R38 -> -- | AC38: =IF(AND(B38="E",R38="U",D38>C38),D38,IF(AND(B38="E",R38="U",D38<=C38),C38,IF(AND(B38="T",R38="U"),D38,IF(AND(B38="E",R38="S",D38>C38),D38,IF(AND(B38="T",R38="S"),D38,0))))) -> 0 | AD38: =IF(B38<>"E",0,IF(D38-C38<0,0,D38-C38)) -> 0
A39: =IF(INPUT!C21="","",INPUT!C21) | B39: =IF(INPUT!D21="","",INPUT!D21) | C39: =IF(INPUT!E21="","",INPUT!E21) | D39: =IF(INPUT!G21="","",INPUT!G21) | E39: =IF(INPUT!L21="","",INPUT!L21) | F39: =IF(INPUT!M21="","",INPUT!M21) | G39: =IF(H39="","",CONCATENATE(IF(INPUT!N21="","",INPUT!N21)," - ",TEXT(H39,"0,00"))) | H39: =IF(A39="","",IF(P39="y",INPUT!P21,O39)) | I39: =IFERROR(VLOOKUP(S39,Formulas!$T$2:$U$77,2,0),"") | J39: =IF(F39="",0,(F39-E39)/(365.25/12)) -> 0 | K39: =IF(E39="",0,(TODAY()-E39)/(365.25/12)) -> 0 | L39: =IF(AND(R39="U",NOT(E39="")),E39,"") | M39: =IF(AND(R39="S",NOT(E39="")),E39,"") | N39: =IF(AND(OR(A39=38,A39=54,A39=5,A39=8),R39="U"),C39,"") | O39: =IFERROR(IF(B39="E",(C39*0.05)+AD39,PMT(VLOOKUP(S39,Formulas!T:U,2,0)/12,J39,-C39)),0) -> 0 | P39: =INPUT!B21 | Q39: =IF(AND(OR(A39=38,A39=54,A39=5,A39=8),R39="S"),C39,"") | R39: =INPUT!N21 | S39: =A39&"-"&B39&"-"&R39 -> -- | AC39: =IF(AND(B39="E",R39="U",D39>C39),D39,IF(AND(B39="E",R39="U",D39<=C39),C39,IF(AND(B39="T",R39="U"),D39,IF(AND(B39="E",R39="S",D39>C39),D39,IF(AND(B39="T",R39="S"),D39,0))))) -> 0 | AD39: =IF(B39<>"E",0,IF(D39-C39<0,0,D39-C39)) -> 0
A40: =IF(INPUT!C22="","",INPUT!C22) | B40: =IF(INPUT!D22="","",INPUT!D22) | C40: =IF(INPUT!E22="","",INPUT!E22) | D40: =IF(INPUT!G22="","",INPUT!G22) | E40: =IF(INPUT!L22="","",INPUT!L22) | F40: =IF(INPUT!M22="","",INPUT!M22) | I40: =IFERROR(VLOOKUP(S40,Formulas!$T$2:$U$77,2,0),"") | J40: =IF(F40="",0,(F40-E40)/(365.25/12)) -> 0 | K40: =IF(E40="",0,(TODAY()-E40)/(365.25/12)) -> 0 | L40: =IF(AND(R40="U",NOT(E40="")),E40,"") | M40: =IF(AND(R40="S",NOT(E40="")),E40,"") | N40: =IF(AND(OR(A40=38,A40=54,A40=5,A40=8),R40="U"),C40,"") | O40: =IFERROR(IF(B40="E",(C40*0.05)+AD40,PMT(VLOOKUP(S40,Formulas!T:U,2,0)/12,J40,-C40)),0) -> 0 | P40: =INPUT!B22 | Q40: =IF(AND(OR(A40=38,A40=54,A40=5,A40=8),R40="S"),C40,"") | R40: =INPUT!N22 | S40: =A40&"-"&B40&"-"&R40 -> -- | AC40: =IF(AND(B40="E",R40="U",D40>C40),D40,IF(AND(B40="E",R40="U",D40<=C40),C40,IF(AND(B40="T",R40="U"),D40,IF(AND(B40="E",R40="S",D40>C40),D40,IF(AND(B40="T",R40="S"),D40,0))))) -> 0 | AD40: =IF(B40<>"E",0,IF(D40-C40<0,0,D40-C40)) -> 0
A41: =IF(INPUT!C23="","",INPUT!C23) | B41: =IF(INPUT!D23="","",INPUT!D23) | C41: =IF(INPUT!E23="","",INPUT!E23) | D41: =IF(INPUT!G23="","",INPUT!G23) | E41: =IF(INPUT!L23="","",INPUT!L23) | F41: =IF(INPUT!M23="","",INPUT!M23) | G41: =IF(H41="","",CONCATENATE(IF(INPUT!N23="","",INPUT!N23)," - ",TEXT(H41,"0,00"))) | H41: =IF(A41="","",IF(P41="y",INPUT!P23,O41)) | I41: =IFERROR(VLOOKUP(S41,Formulas!$T$2:$U$77,2,0),"") | J41: =IF(F41="",0,(F41-E41)/(365.25/12)) -> 0 | K41: =IF(E41="",0,(TODAY()-E41)/(365.25/12)) -> 0 | L41: =IF(AND(R41="U",NOT(E41="")),E41,"") | M41: =IF(AND(R41="S",NOT(E41="")),E41,"") | N41: =IF(AND(OR(A41=38,A41=54,A41=5,A41=8),R41="U"),C41,"") | O41: =IFERROR(IF(B41="E",(C41*0.05)+AD41,PMT(VLOOKUP(S41,Formulas!T:U,2,0)/12,J41,-C41)),0) -> 0 | P41: =INPUT!B23 | Q41: =IF(AND(OR(A41=38,A41=54,A41=5,A41=8),R41="S"),C41,"") | R41: =INPUT!N23 | S41: =A41&"-"&B41&"-"&R41 -> -- | AC41: =IF(AND(B41="E",R41="U",D41>C41),D41,IF(AND(B41="E",R41="U",D41<=C41),C41,IF(AND(B41="T",R41="U"),D41,IF(AND(B41="E",R41="S",D41>C41),D41,IF(AND(B41="T",R41="S"),D41,0))))) -> 0 | AD41: =IF(B41<>"E",0,IF(D41-C41<0,0,D41-C41)) -> 0
A42: =IF(INPUT!C24="","",INPUT!C24) | B42: =IF(INPUT!D24="","",INPUT!D24) | C42: =IF(INPUT!E24="","",INPUT!E24) | D42: =IF(INPUT!G24="","",INPUT!G24) | E42: =IF(INPUT!L24="","",INPUT!L24) | F42: =IF(INPUT!M24="","",INPUT!M24) | G42: =IF(H42="","",CONCATENATE(IF(INPUT!N24="","",INPUT!N24)," - ",TEXT(H42,"0,00"))) | H42: =IF(A42="","",IF(P42="y",INPUT!P24,O42)) | I42: =IFERROR(VLOOKUP(S42,Formulas!$T$2:$U$77,2,0),"") | J42: =IF(F42="",0,(F42-E42)/(365.25/12)) -> 0 | K42: =IF(E42="",0,(TODAY()-E42)/(365.25/12)) -> 0 | L42: =IF(AND(R42="U",NOT(E42="")),E42,"") | M42: =IF(AND(R42="S",NOT(E42="")),E42,"") | N42: =IF(AND(OR(A42=38,A42=54,A42=5,A42=8),R42="U"),C42,"") | O42: =IFERROR(IF(B42="E",(C42*0.05)+AD42,PMT(VLOOKUP(S42,Formulas!T:U,2,0)/12,J42,-C42)),0) -> 0 | P42: =INPUT!B24 | Q42: =IF(AND(OR(A42=38,A42=54,A42=5,A42=8),R42="S"),C42,"") | R42: =INPUT!N24 | S42: =A42&"-"&B42&"-"&R42 -> -- | AC42: =IF(AND(B42="E",R42="U",D42>C42),D42,IF(AND(B42="E",R42="U",D42<=C42),C42,IF(AND(B42="T",R42="U"),D42,IF(AND(B42="E",R42="S",D42>C42),D42,IF(AND(B42="T",R42="S"),D42,0))))) -> 0 | AD42: =IF(B42<>"E",0,IF(D42-C42<0,0,D42-C42)) -> 0
A43: =IF(INPUT!C25="","",INPUT!C25) | B43: =IF(INPUT!D25="","",INPUT!D25) | C43: =IF(INPUT!E25="","",INPUT!E25) | D43: =IF(INPUT!G25="","",INPUT!G25) | E43: =IF(INPUT!L25="","",INPUT!L25) | F43: =IF(INPUT!M25="","",INPUT!M25) | G43: =IF(H43="","",CONCATENATE(IF(INPUT!N25="","",INPUT!N25)," - ",TEXT(H43,"0,00"))) | H43: =IF(A43="","",IF(P43="y",INPUT!P25,O43)) | I43: =IFERROR(VLOOKUP(S43,Formulas!$T$2:$U$77,2,0),"") | J43: =IF(F43="",0,(F43-E43)/(365.25/12)) -> 0 | K43: =IF(E43="",0,(TODAY()-E43)/(365.25/12)) -> 0 | L43: =IF(AND(R43="U",NOT(E43="")),E43,"") | M43: =IF(AND(R43="S",NOT(E43="")),E43,"") | N43: =IF(AND(OR(A43=38,A43=54,A43=5,A43=8),R43="U"),C43,"") | O43: =IFERROR(IF(B43="E",(C43*0.05)+AD43,PMT(VLOOKUP(S43,Formulas!T:U,2,0)/12,J43,-C43)),0) -> 0 | P43: =INPUT!B25 | Q43: =IF(AND(OR(A43=38,A43=54,A43=5,A43=8),R43="S"),C43,"") | R43: =INPUT!N25 | S43: =A43&"-"&B43&"-"&R43 -> -- | AC43: =IF(AND(B43="E",R43="U",D43>C43),D43,IF(AND(B43="E",R43="U",D43<=C43),C43,IF(AND(B43="T",R43="U"),D43,IF(AND(B43="E",R43="S",D43>C43),D43,IF(AND(B43="T",R43="S"),D43,0))))) -> 0 | AD43: =IF(B43<>"E",0,IF(D43-C43<0,0,D43-C43)) -> 0
A44: =IF(INPUT!C26="","",INPUT!C26) | B44: =IF(INPUT!D26="","",INPUT!D26) | C44: =IF(INPUT!E26="","",INPUT!E26) | D44: =IF(INPUT!G26="","",INPUT!G26) | E44: =IF(INPUT!L26="","",INPUT!L26) | F44: =IF(INPUT!M26="","",INPUT!M26) | G44: =IF(H44="","",CONCATENATE(IF(INPUT!N26="","",INPUT!N26)," - ",TEXT(H44,"0,00"))) | H44: =IF(A44="","",IF(P44="y",INPUT!P26,O44)) | I44: =IFERROR(VLOOKUP(S44,Formulas!$T$2:$U$77,2,0),"") | J44: =IF(F44="",0,(F44-E44)/(365.25/12)) -> 0 | K44: =IF(E44="",0,(TODAY()-E44)/(365.25/12)) -> 0 | L44: =IF(AND(R44="U",NOT(E44="")),E44,"") | M44: =IF(AND(R44="S",NOT(E44="")),E44,"") | N44: =IF(AND(OR(A44=38,A44=54,A44=5,A44=8),R44="U"),C44,"") | O44: =IFERROR(IF(B44="E",(C44*0.05)+AD44,PMT(VLOOKUP(S44,Formulas!T:U,2,0)/12,J44,-C44)),0) -> 0 | P44: =INPUT!B26 | Q44: =IF(AND(OR(A44=38,A44=54,A44=5,A44=8),R44="S"),C44,"") | R44: =INPUT!N26 | S44: =A44&"-"&B44&"-"&R44 -> -- | AC44: =IF(AND(B44="E",R44="U",D44>C44),D44,IF(AND(B44="E",R44="U",D44<=C44),C44,IF(AND(B44="T",R44="U"),D44,IF(AND(B44="E",R44="S",D44>C44),D44,IF(AND(B44="T",R44="S"),D44,0))))) -> 0 | AD44: =IF(B44<>"E",0,IF(D44-C44<0,0,D44-C44)) -> 0
A45: =IF(INPUT!C27="","",INPUT!C27) | B45: =IF(INPUT!D27="","",INPUT!D27) | C45: =IF(INPUT!E27="","",INPUT!E27) | D45: =IF(INPUT!G27="","",INPUT!G27) | E45: =IF(INPUT!L27="","",INPUT!L27) | F45: =IF(INPUT!M27="","",INPUT!M27) | G45: =IF(H45="","",CONCATENATE(IF(INPUT!N27="","",INPUT!N27)," - ",TEXT(H45,"0,00"))) | H45: =IF(A45="","",IF(P45="y",INPUT!P27,O45)) | I45: =IFERROR(VLOOKUP(S45,Formulas!$T$2:$U$77,2,0),"") | J45: =IF(F45="",0,(F45-E45)/(365.25/12)) -> 0 | K45: =IF(E45="",0,(TODAY()-E45)/(365.25/12)) -> 0 | L45: =IF(AND(R45="U",NOT(E45="")),E45,"") | M45: =IF(AND(R45="S",NOT(E45="")),E45,"") | N45: =IF(AND(OR(A45=38,A45=54,A45=5,A45=8),R45="U"),C45,"") | O45: =IFERROR(IF(B45="E",(C45*0.05)+AD45,PMT(VLOOKUP(S45,Formulas!T:U,2,0)/12,J45,-C45)),0) -> 0 | P45: =INPUT!B27 | Q45: =IF(AND(OR(A45=38,A45=54,A45=5,A45=8),R45="S"),C45,"") | R45: =INPUT!N27 | S45: =A45&"-"&B45&"-"&R45 -> -- | AC45: =IF(AND(B45="E",R45="U",D45>C45),D45,IF(AND(B45="E",R45="U",D45<=C45),C45,IF(AND(B45="T",R45="U"),D45,IF(AND(B45="E",R45="S",D45>C45),D45,IF(AND(B45="T",R45="S"),D45,0))))) -> 0 | AD45: =IF(B45<>"E",0,IF(D45-C45<0,0,D45-C45)) -> 0
A46: =IF(INPUT!C28="","",INPUT!C28) | B46: =IF(INPUT!D28="","",INPUT!D28) | C46: =IF(INPUT!E28="","",INPUT!E28) | D46: =IF(INPUT!G28="","",INPUT!G28) | E46: =IF(INPUT!L28="","",INPUT!L28) | F46: =IF(INPUT!M28="","",INPUT!M28) | G46: =IF(H46="","",CONCATENATE(IF(INPUT!N28="","",INPUT!N28)," - ",TEXT(H46,"0,00"))) | H46: =IF(A46="","",IF(P46="y",INPUT!P28,O46)) | I46: =IFERROR(VLOOKUP(S46,Formulas!$T$2:$U$77,2,0),"") | J46: =IF(F46="",0,(F46-E46)/(365.25/12)) -> 0 | K46: =IF(E46="",0,(TODAY()-E46)/(365.25/12)) -> 0 | L46: =IF(AND(R46="U",NOT(E46="")),E46,"") | M46: =IF(AND(R46="S",NOT(E46="")),E46,"") | N46: =IF(AND(OR(A46=38,A46=54,A46=5,A46=8),R46="U"),C46,"") | O46: =IFERROR(IF(B46="E",(C46*0.05)+AD46,PMT(VLOOKUP(S46,Formulas!T:U,2,0)/12,J46,-C46)),0) -> 0 | P46: =INPUT!B28 | Q46: =IF(AND(OR(A46=38,A46=54,A46=5,A46=8),R46="S"),C46,"") | R46: =INPUT!N28 | S46: =A46&"-"&B46&"-"&R46 -> -- | AC46: =IF(AND(B46="E",R46="U",D46>C46),D46,IF(AND(B46="E",R46="U",D46<=C46),C46,IF(AND(B46="T",R46="U"),D46,IF(AND(B46="E",R46="S",D46>C46),D46,IF(AND(B46="T",R46="S"),D46,0))))) -> 0 | AD46: =IF(B46<>"E",0,IF(D46-C46<0,0,D46-C46)) -> 0
A47: =IF(INPUT!C29="","",INPUT!C29) | B47: =IF(INPUT!D29="","",INPUT!D29) | C47: =IF(INPUT!E29="","",INPUT!E29) | D47: =IF(INPUT!G29="","",INPUT!G29) | E47: =IF(INPUT!L29="","",INPUT!L29) | F47: =IF(INPUT!M29="","",INPUT!M29) | G47: =IF(H47="","",CONCATENATE(IF(INPUT!N29="","",INPUT!N29)," - ",TEXT(H47,"0,00"))) | H47: =IF(A47="","",IF(P47="y",INPUT!P29,O47)) | I47: =IFERROR(VLOOKUP(S47,Formulas!$T$2:$U$77,2,0),"") | J47: =IF(F47="",0,(F47-E47)/(365.25/12)) -> 0 | K47: =IF(E47="",0,(TODAY()-E47)/(365.25/12)) -> 0 | L47: =IF(AND(R47="U",NOT(E47="")),E47,"") | M47: =IF(AND(R47="S",NOT(E47="")),E47,"") | N47: =IF(AND(OR(A47=38,A47=54,A47=5,A47=8),R47="U"),C47,"") | O47: =IFERROR(IF(B47="E",(C47*0.05)+AD47,PMT(VLOOKUP(S47,Formulas!T:U,2,0)/12,J47,-C47)),0) -> 0 | P47: =INPUT!B29 | Q47: =IF(AND(OR(A47=38,A47=54,A47=5,A47=8),R47="S"),C47,"") | R47: =INPUT!N29 | S47: =A47&"-"&B47&"-"&R47 -> -- | AC47: =IF(AND(B47="E",R47="U",D47>C47),D47,IF(AND(B47="E",R47="U",D47<=C47),C47,IF(AND(B47="T",R47="U"),D47,IF(AND(B47="E",R47="S",D47>C47),D47,IF(AND(B47="T",R47="S"),D47,0))))) -> 0 | AD47: =IF(B47<>"E",0,IF(D47-C47<0,0,D47-C47)) -> 0
A48: =IF(INPUT!C30="","",INPUT!C30) | B48: =IF(INPUT!D30="","",INPUT!D30) | C48: =IF(INPUT!E30="","",INPUT!E30) | D48: =IF(INPUT!G30="","",INPUT!G30) | E48: =IF(INPUT!L30="","",INPUT!L30) | F48: =IF(INPUT!M30="","",INPUT!M30) | G48: =IF(H48="","",CONCATENATE(IF(INPUT!N30="","",INPUT!N30)," - ",TEXT(H48,"0,00"))) | H48: =IF(A48="","",IF(P48="y",INPUT!P30,O48)) | I48: =IFERROR(VLOOKUP(S48,Formulas!$T$2:$U$77,2,0),"") | J48: =IF(F48="",0,(F48-E48)/(365.25/12)) -> 0 | K48: =IF(E48="",0,(TODAY()-E48)/(365.25/12)) -> 0 | L48: =IF(AND(R48="U",NOT(E48="")),E48,"") | M48: =IF(AND(R48="S",NOT(E48="")),E48,"") | N48: =IF(AND(OR(A48=38,A48=54,A48=5,A48=8),R48="U"),C48,"") | O48: =IFERROR(IF(B48="E",(C48*0.05)+AD48,PMT(VLOOKUP(S48,Formulas!T:U,2,0)/12,J48,-C48)),0) -> 0 | P48: =INPUT!B30 | Q48: =IF(AND(OR(A48=38,A48=54,A48=5,A48=8),R48="S"),C48,"") | R48: =INPUT!N30 | S48: =A48&"-"&B48&"-"&R48 -> -- | AC48: =IF(AND(B48="E",R48="U",D48>C48),D48,IF(AND(B48="E",R48="U",D48<=C48),C48,IF(AND(B48="T",R48="U"),D48,IF(AND(B48="E",R48="S",D48>C48),D48,IF(AND(B48="T",R48="S"),D48,0))))) -> 0 | AD48: =IF(B48<>"E",0,IF(D48-C48<0,0,D48-C48)) -> 0
A49: =IF(INPUT!C31="","",INPUT!C31) | B49: =IF(INPUT!D31="","",INPUT!D31) | C49: =IF(INPUT!E31="","",INPUT!E31) | D49: =IF(INPUT!G31="","",INPUT!G31) | E49: =IF(INPUT!L31="","",INPUT!L31) | F49: =IF(INPUT!M31="","",INPUT!M31) | G49: =IF(H49="","",CONCATENATE(IF(INPUT!N31="","",INPUT!N31)," - ",TEXT(H49,"0,00"))) | H49: =IF(A49="","",IF(P49="y",INPUT!P31,O49)) | I49: =IFERROR(VLOOKUP(S49,Formulas!$T$2:$U$77,2,0),"") | J49: =IF(F49="",0,(F49-E49)/(365.25/12)) -> 0 | K49: =IF(E49="",0,(TODAY()-E49)/(365.25/12)) -> 0 | L49: =IF(AND(R49="U",NOT(E49="")),E49,"") | M49: =IF(AND(R49="S",NOT(E49="")),E49,"") | N49: =IF(AND(OR(A49=38,A49=54,A49=5,A49=8),R49="U"),C49,"") | O49: =IFERROR(IF(B49="E",(C49*0.05)+AD49,PMT(VLOOKUP(S49,Formulas!T:U,2,0)/12,J49,-C49)),0) -> 0 | P49: =INPUT!B31 | Q49: =IF(AND(OR(A49=38,A49=54,A49=5,A49=8),R49="S"),C49,"") | R49: =INPUT!N31 | S49: =A49&"-"&B49&"-"&R49 -> -- | AC49: =IF(AND(B49="E",R49="U",D49>C49),D49,IF(AND(B49="E",R49="U",D49<=C49),C49,IF(AND(B49="T",R49="U"),D49,IF(AND(B49="E",R49="S",D49>C49),D49,IF(AND(B49="T",R49="S"),D49,0))))) -> 0 | AD49: =IF(B49<>"E",0,IF(D49-C49<0,0,D49-C49)) -> 0
A50: =IF(INPUT!C32="","",INPUT!C32) | B50: =IF(INPUT!D32="","",INPUT!D32) | C50: =IF(INPUT!E32="","",INPUT!E32) | D50: =IF(INPUT!G32="","",INPUT!G32) | E50: =IF(INPUT!L32="","",INPUT!L32) | F50: =IF(INPUT!M32="","",INPUT!M32) | G50: =IF(H50="","",CONCATENATE(IF(INPUT!N32="","",INPUT!N32)," - ",TEXT(H50,"0,00"))) | H50: =IF(A50="","",IF(P50="y",INPUT!P32,O50)) | I50: =IFERROR(VLOOKUP(S50,Formulas!$T$2:$U$77,2,0),"") | J50: =IF(F50="",0,(F50-E50)/(365.25/12)) -> 0 | K50: =IF(E50="",0,(TODAY()-E50)/(365.25/12)) -> 0 | L50: =IF(AND(R50="U",NOT(E50="")),E50,"") | M50: =IF(AND(R50="S",NOT(E50="")),E50,"") | N50: =IF(AND(OR(A50=38,A50=54,A50=5,A50=8),R50="U"),C50,"") | O50: =IFERROR(IF(B50="E",(C50*0.05)+AD50,PMT(VLOOKUP(S50,Formulas!T:U,2,0)/12,J50,-C50)),0) -> 0 | P50: =INPUT!B32 | Q50: =IF(AND(OR(A50=38,A50=54,A50=5,A50=8),R50="S"),C50,"") | R50: =INPUT!N32 | S50: =A50&"-"&B50&"-"&R50 -> -- | AC50: =IF(AND(B50="E",R50="U",D50>C50),D50,IF(AND(B50="E",R50="U",D50<=C50),C50,IF(AND(B50="T",R50="U"),D50,IF(AND(B50="E",R50="S",D50>C50),D50,IF(AND(B50="T",R50="S"),D50,0))))) -> 0 | AD50: =IF(B50<>"E",0,IF(D50-C50<0,0,D50-C50)) -> 0
A51: =IF(INPUT!C33="","",INPUT!C33) | B51: =IF(INPUT!D33="","",INPUT!D33) | C51: =IF(INPUT!E33="","",INPUT!E33) | D51: =IF(INPUT!G33="","",INPUT!G33) | E51: =IF(INPUT!L33="","",INPUT!L33) | F51: =IF(INPUT!M33="","",INPUT!M33) | G51: =IF(H51="","",CONCATENATE(IF(INPUT!N33="","",INPUT!N33)," - ",TEXT(H51,"0,00"))) | H51: =IF(A51="","",IF(P51="y",INPUT!P33,O51)) | I51: =IFERROR(VLOOKUP(S51,Formulas!$T$2:$U$77,2,0),"") | J51: =IF(F51="",0,(F51-E51)/(365.25/12)) -> 0 | K51: =IF(E51="",0,(TODAY()-E51)/(365.25/12)) -> 0 | L51: =IF(AND(R51="U",NOT(E51="")),E51,"") | M51: =IF(AND(R51="S",NOT(E51="")),E51,"") | N51: =IF(AND(OR(A51=38,A51=54,A51=5,A51=8),R51="U"),C51,"") | O51: =IFERROR(IF(B51="E",(C51*0.05)+AD51,PMT(VLOOKUP(S51,Formulas!T:U,2,0)/12,J51,-C51)),0) -> 0 | P51: =INPUT!B33 | Q51: =IF(AND(OR(A51=38,A51=54,A51=5,A51=8),R51="S"),C51,"") | R51: =INPUT!N33 | S51: =A51&"-"&B51&"-"&R51 -> -- | AC51: =IF(AND(B51="E",R51="U",D51>C51),D51,IF(AND(B51="E",R51="U",D51<=C51),C51,IF(AND(B51="T",R51="U"),D51,IF(AND(B51="E",R51="S",D51>C51),D51,IF(AND(B51="T",R51="S"),D51,0))))) -> 0 | AD51: =IF(B51<>"E",0,IF(D51-C51<0,0,D51-C51)) -> 0
A52: =IF(INPUT!C34="","",INPUT!C34) | B52: =IF(INPUT!D34="","",INPUT!D34) | C52: =IF(INPUT!E34="","",INPUT!E34) | D52: =IF(INPUT!G34="","",INPUT!G34) | E52: =IF(INPUT!L34="","",INPUT!L34) | F52: =IF(INPUT!M34="","",INPUT!M34) | G52: =IF(H52="","",CONCATENATE(IF(INPUT!N34="","",INPUT!N34)," - ",TEXT(H52,"0,00"))) | H52: =IF(A52="","",IF(P52="y",INPUT!P34,O52)) | I52: =IFERROR(VLOOKUP(S52,Formulas!$T$2:$U$77,2,0),"") | J52: =IF(F52="",0,(F52-E52)/(365.25/12)) -> 0 | K52: =IF(E52="",0,(TODAY()-E52)/(365.25/12)) -> 0 | L52: =IF(AND(R52="U",NOT(E52="")),E52,"") | M52: =IF(AND(R52="S",NOT(E52="")),E52,"") | N52: =IF(AND(OR(A52=38,A52=54,A52=5,A52=8),R52="U"),C52,"") | O52: =IFERROR(IF(B52="E",(C52*0.05)+AD52,PMT(VLOOKUP(S52,Formulas!T:U,2,0)/12,J52,-C52)),0) -> 0 | P52: =INPUT!B34 | Q52: =IF(AND(OR(A52=38,A52=54,A52=5,A52=8),R52="S"),C52,"") | R52: =INPUT!N34 | S52: =A52&"-"&B52&"-"&R52 -> -- | AC52: =IF(AND(B52="E",R52="U",D52>C52),D52,IF(AND(B52="E",R52="U",D52<=C52),C52,IF(AND(B52="T",R52="U"),D52,IF(AND(B52="E",R52="S",D52>C52),D52,IF(AND(B52="T",R52="S"),D52,0))))) -> 0 | AD52: =IF(B52<>"E",0,IF(D52-C52<0,0,D52-C52)) -> 0
... A54: =IF(INPUT!C36="","",INPUT!C36) | B54: =IF(INPUT!D36="","",INPUT!D36) | C54: =IF(INPUT!E36="","",INPUT!E36) | D54: =IF(INPUT!G36="","",INPUT!G36) | E54: =IF(INPUT!L36="","",INPUT!L36) | F54: =IF(INPUT!M36="","",INPUT!M36) | G54: =IF(H54="","",CONCATENATE(IF(INPUT!N36="","",INPUT!N36)," - ",TEXT(H54,"0,00"))) | H54: =IF(A54="","",IF(P54="y",INPUT!P36,O54)) | I54: =IFERROR(VLOOKUP(S54,Formulas!$T$2:$U$77,2,0),"") | J54: =IF(F54="",0,(F54-E54)/(365.25/12)) -> 0 | K54: =IF(E54="",0,(TODAY()-E54)/(365.25/12)) -> 0 | L54: =IF(AND(R54="U",NOT(E54="")),E54,"") | M54: =IF(AND(R54="S",NOT(E54="")),E54,"") | N54: =IF(AND(OR(A54=38,A54=54,A54=5,A54=8),R54="U"),C54,"") | O54: =IFERROR(IF(B54="E",(C54*0.05)+AD54,PMT(VLOOKUP(S54,Formulas!T:U,2,0)/12,J54,-C54)),0) -> 0 | P54: =INPUT!B36 | Q54: =IF(AND(OR(A54=38,A54=54,A54=5,A54=8),R54="S"),C54,"") | R54: =INPUT!N36 | S54: =A54&"-"&B54&"-"&R54 -> -- | AC54: =IF(AND(B54="E",R54="U",D54>C54),D54,IF(AND(B54="E",R54="U",D54<=C54),C54,IF(AND(B54="T",R54="U"),D54,IF(AND(B54="E",R54="S",D54>C54),D54,IF(AND(B54="T",R54="S"),D54,0))))) -> 0 | AD54: =IF(B54<>"E",0,IF(D54-C54<0,0,D54-C54)) -> 0
A55: =IF(ECIB!B28="","",ECIB!B28) | B55: =IF(ECIB!C28="","",ECIB!C28) | C55: =IF(INPUT!E37="","",INPUT!E37) | D55: =IF(INPUT!G37="","",INPUT!G37) | E55: =IF(ECIB!K28="","",ECIB!K28) | F55: =IF(ECIB!L28="","",ECIB!L28) | G55: =IF(H55="","",CONCATENATE(IF(ECIB!M28="","",ECIB!M28)," - ",TEXT(H55,"0,00"))) | H55: =IF(A55="","",IF(P55="y",ECIB!X28,O55)) | I55: =IFERROR(VLOOKUP(S55,Formulas!$T$2:$U$77,2,0),"") | J55: =IF(F55="",0,(F55-E55)/(365.25/12)) -> 0 | K55: =IF(E55="",0,(TODAY()-E55)/(365.25/12)) -> 0 | L55: =IF(AND(R55="U",NOT(E55="")),E55,"") | M55: =IF(AND(R55="S",NOT(E55="")),E55,"") | N55: =IF(AND(OR(A55=38,A55=54,A55=5,A55=8),R55="U"),C55,"") | O55: =IFERROR(IF(B55="E",(C55*0.05)+AD55,PMT(VLOOKUP(S55,Formulas!T:U,2,0)/12,J55,-C55)),0) -> 0 | P55: =ECIB!A28 | Q55: =IF(AND(OR(A55=38,A55=54,A55=5,A55=8),R55="S"),C55,"") | R55: =ECIB!M28 | S55: =A55&"-"&B55&"-"&R55 -> -- | AC55: =IF(AND(B55="E",R55="U",D55>C55),D55,IF(AND(B55="E",R55="U",D55<=C55),C55,IF(AND(B55="T",R55="U"),D55,IF(AND(B55="E",R55="S",D55>C55),D55,IF(AND(B55="T",R55="S"),D55,0))))) -> 0 | AD55: =IF(B55<>"E",0,IF(D55-C55<0,0,D55-C55)) -> 0
A56: =IF(ECIB!B29="","",ECIB!B29) | B56: =IF(ECIB!C29="","",ECIB!C29) | C56: =IF(INPUT!E38="","",INPUT!E38) | D56: =IF(INPUT!G38="","",INPUT!G38) | E56: =IF(ECIB!K29="","",ECIB!K29) | F56: =IF(ECIB!L29="","",ECIB!L29) | G56: =IF(H56="","",CONCATENATE(IF(ECIB!M29="","",ECIB!M29)," - ",TEXT(H56,"0,00"))) | H56: =IF(A56="","",IF(P56="y",ECIB!X29,O56)) | I56: =IFERROR(VLOOKUP(S56,Formulas!$T$2:$U$77,2,0),"") | J56: =IF(F56="",0,(F56-E56)/(365.25/12)) -> 0 | K56: =IF(E56="",0,(TODAY()-E56)/(365.25/12)) -> 0 | L56: =IF(AND(R56="U",NOT(E56="")),E56,"") | M56: =IF(AND(R56="S",NOT(E56="")),E56,"") | N56: =IF(AND(OR(A56=38,A56=54,A56=5,A56=8),R56="U"),C56,"") | O56: =IFERROR(IF(B56="E",(C56*0.05)+AD56,PMT(VLOOKUP(S56,Formulas!T:U,2,0)/12,J56,-C56)),0) -> 0 | P56: =ECIB!A29 | Q56: =IF(AND(OR(A56=38,A56=54,A56=5,A56=8),R56="S"),C56,"") | R56: =ECIB!M29 | S56: =A56&"-"&B56&"-"&R56 -> -- | AC56: =IF(AND(B56="E",R56="U",D56>C56),D56,IF(AND(B56="E",R56="U",D56<=C56),C56,IF(AND(B56="T",R56="U"),D56,IF(AND(B56="E",R56="S",D56>C56),D56,IF(AND(B56="T",R56="S"),D56,0))))) -> 0 | AD56: =IF(B56<>"E",0,IF(D56-C56<0,0,D56-C56)) -> 0
A57: =IF(ECIB!B30="","",ECIB!B30) | B57: =IF(ECIB!C30="","",ECIB!C30) | C57: =IF(INPUT!E39="","",INPUT!E39) | D57: =IF(INPUT!G39="","",INPUT!G39) | E57: =IF(ECIB!K30="","",ECIB!K30) | F57: =IF(ECIB!L30="","",ECIB!L30) | G57: =IF(H57="","",CONCATENATE(IF(ECIB!M30="","",ECIB!M30)," - ",TEXT(H57,"0,00"))) | H57: =IF(A57="","",IF(P57="y",ECIB!X30,O57)) | I57: =IFERROR(VLOOKUP(S57,Formulas!$T$2:$U$77,2,0),"") | J57: =IF(F57="",0,(F57-E57)/(365.25/12)) -> 0 | K57: =IF(E57="",0,(TODAY()-E57)/(365.25/12)) -> 0 | L57: =IF(AND(R57="U",NOT(E57="")),E57,"") | M57: =IF(AND(R57="S",NOT(E57="")),E57,"") | N57: =IF(AND(OR(A57=38,A57=54,A57=5,A57=8),R57="U"),C57,"") | O57: =IFERROR(IF(B57="E",(C57*0.05)+AD57,PMT(VLOOKUP(S57,Formulas!T:U,2,0)/12,J57,-C57)),0) -> 0 | P57: =ECIB!A30 | Q57: =IF(AND(OR(A57=38,A57=54,A57=5,A57=8),R57="S"),C57,"") | R57: =ECIB!M30 | S57: =A57&"-"&B57&"-"&R57 -> -- | AC57: =IF(AND(B57="E",R57="U",D57>C57),D57,IF(AND(B57="E",R57="U",D57<=C57),C57,IF(AND(B57="T",R57="U"),D57,IF(AND(B57="E",R57="S",D57>C57),D57,IF(AND(B57="T",R57="S"),D57,0))))) -> 0 | AD57: =IF(B57<>"E",0,IF(D57-C57<0,0,D57-C57)) -> 0
A58: =IF(ECIB!B31="","",ECIB!B31) | B58: =IF(ECIB!C31="","",ECIB!C31) | C58: =IF(INPUT!E40="","",INPUT!E40) | D58: =IF(INPUT!G40="","",INPUT!G40) | E58: =IF(ECIB!K31="","",ECIB!K31) | F58: =IF(ECIB!L31="","",ECIB!L31) | G58: =IF(H58="","",CONCATENATE(IF(ECIB!M31="","",ECIB!M31)," - ",TEXT(H58,"0,00"))) | H58: =IF(A58="","",IF(P58="y",ECIB!X31,O58)) | I58: =IFERROR(VLOOKUP(S58,Formulas!$T$2:$U$77,2,0),"") | J58: =IF(F58="",0,(F58-E58)/(365.25/12)) -> 0 | K58: =IF(E58="",0,(TODAY()-E58)/(365.25/12)) -> 0 | L58: =IF(AND(R58="U",NOT(E58="")),E58,"") | M58: =IF(AND(R58="S",NOT(E58="")),E58,"") | N58: =IF(AND(OR(A58=38,A58=54,A58=5,A58=8),R58="U"),C58,"") | O58: =IFERROR(IF(B58="E",(C58*0.05)+AD58,PMT(VLOOKUP(S58,Formulas!T:U,2,0)/12,J58,-C58)),0) -> 0 | P58: =ECIB!A31 | Q58: =IF(AND(OR(A58=38,A58=54,A58=5,A58=8),R58="S"),C58,"") | R58: =ECIB!M31 | S58: =A58&"-"&B58&"-"&R58 -> -- | AC58: =IF(AND(B58="E",R58="U",D58>C58),D58,IF(AND(B58="E",R58="U",D58<=C58),C58,IF(AND(B58="T",R58="U"),D58,IF(AND(B58="E",R58="S",D58>C58),D58,IF(AND(B58="T",R58="S"),D58,0))))) -> 0 | AD58: =IF(B58<>"E",0,IF(D58-C58<0,0,D58-C58)) -> 0
A59: =IF(ECIB!B32="","",ECIB!B32) | B59: =IF(ECIB!C32="","",ECIB!C32) | C59: =IF(INPUT!E41="","",INPUT!E41) | D59: =IF(INPUT!G41="","",INPUT!G41) | E59: =IF(ECIB!K32="","",ECIB!K32) | F59: =IF(ECIB!L32="","",ECIB!L32) | G59: =IF(H59="","",CONCATENATE(IF(ECIB!M32="","",ECIB!M32)," - ",TEXT(H59,"0,00"))) | H59: =IF(A59="","",IF(P59="y",ECIB!X32,O59)) | I59: =IFERROR(VLOOKUP(S59,Formulas!$T$2:$U$77,2,0),"") | J59: =IF(F59="",0,(F59-E59)/(365.25/12)) -> 0 | K59: =IF(E59="",0,(TODAY()-E59)/(365.25/12)) -> 0 | L59: =IF(AND(R59="U",NOT(E59="")),E59,"") | M59: =IF(AND(R59="S",NOT(E59="")),E59,"") | N59: =IF(AND(OR(A59=38,A59=54,A59=5,A59=8),R59="U"),C59,"") | O59: =IFERROR(IF(B59="E",(C59*0.05)+AD59,PMT(VLOOKUP(S59,Formulas!T:U,2,0)/12,J59,-C59)),0) -> 0 | P59: =ECIB!A32 | Q59: =IF(AND(OR(A59=38,A59=54,A59=5,A59=8),R59="S"),C59,"") | R59: =ECIB!M32 | S59: =A59&"-"&B59&"-"&R59 -> -- | AC59: =IF(AND(B59="E",R59="U",D59>C59),D59,IF(AND(B59="E",R59="U",D59<=C59),C59,IF(AND(B59="T",R59="U"),D59,IF(AND(B59="E",R59="S",D59>C59),D59,IF(AND(B59="T",R59="S"),D59,0))))) -> 0 | AD59: =IF(B59<>"E",0,IF(D59-C59<0,0,D59-C59)) -> 0
A60: =IF(ECIB!B33="","",ECIB!B33) | B60: =IF(ECIB!C33="","",ECIB!C33) | C60: =IF(INPUT!E42="","",INPUT!E42) | D60: =IF(INPUT!G42="","",INPUT!G42) | E60: =IF(ECIB!K33="","",ECIB!K33) | F60: =IF(ECIB!L33="","",ECIB!L33) | G60: =IF(H60="","",CONCATENATE(IF(ECIB!M33="","",ECIB!M33)," - ",TEXT(H60,"0,00"))) | H60: =IF(A60="","",IF(P60="y",ECIB!X33,O60)) | I60: =IFERROR(VLOOKUP(S60,Formulas!$T$2:$U$77,2,0),"") | J60: =IF(F60="",0,(F60-E60)/(365.25/12)) -> 0 | K60: =IF(E60="",0,(TODAY()-E60)/(365.25/12)) -> 0 | L60: =IF(AND(R60="U",NOT(E60="")),E60,"") | M60: =IF(AND(R60="S",NOT(E60="")),E60,"") | N60: =IF(AND(OR(A60=38,A60=54,A60=5,A60=8),R60="U"),C60,"") | O60: =IFERROR(IF(B60="E",(C60*0.05)+AD60,PMT(VLOOKUP(S60,Formulas!T:U,2,0)/12,J60,-C60)),0) -> 0 | P60: =ECIB!A33 | Q60: =IF(AND(OR(A60=38,A60=54,A60=5,A60=8),R60="S"),C60,"") | R60: =ECIB!M33 | S60: =A60&"-"&B60&"-"&R60 -> -- | AC60: =IF(AND(B60="E",R60="U",D60>C60),D60,IF(AND(B60="E",R60="U",D60<=C60),C60,IF(AND(B60="T",R60="U"),D60,IF(AND(B60="E",R60="S",D60>C60),D60,IF(AND(B60="T",R60="S"),D60,0))))) -> 0 | AD60: =IF(B60<>"E",0,IF(D60-C60<0,0,D60-C60)) -> 0
A61: =IF(ECIB!B34="","",ECIB!B34) | B61: =IF(ECIB!C34="","",ECIB!C34) | C61: =IF(INPUT!E43="","",INPUT!E43) | D61: =IF(INPUT!G43="","",INPUT!G43) | E61: =IF(ECIB!K34="","",ECIB!K34) | F61: =IF(ECIB!L34="","",ECIB!L34) | G61: =IF(H61="","",CONCATENATE(IF(ECIB!M34="","",ECIB!M34)," - ",TEXT(H61,"0,00"))) | H61: =IF(A61="","",IF(P61="y",ECIB!X34,O61)) | I61: =IFERROR(VLOOKUP(S61,Formulas!$T$2:$U$77,2,0),"") | J61: =IF(F61="",0,(F61-E61)/(365.25/12)) -> 0 | K61: =IF(E61="",0,(TODAY()-E61)/(365.25/12)) -> 0 | L61: =IF(AND(R61="U",NOT(E61="")),E61,"") | M61: =IF(AND(R61="S",NOT(E61="")),E61,"") | N61: =IF(AND(OR(A61=38,A61=54,A61=5,A61=8),R61="U"),C61,"") | O61: =IFERROR(IF(B61="E",(C61*0.05)+AD61,PMT(VLOOKUP(S61,Formulas!T:U,2,0)/12,J61,-C61)),0) -> 0 | P61: =ECIB!A34 | Q61: =IF(AND(OR(A61=38,A61=54,A61=5,A61=8),R61="S"),C61,"") | R61: =ECIB!M34 | S61: =A61&"-"&B61&"-"&R61 -> -- | AC61: =IF(AND(B61="E",R61="U",D61>C61),D61,IF(AND(B61="E",R61="U",D61<=C61),C61,IF(AND(B61="T",R61="U"),D61,IF(AND(B61="E",R61="S",D61>C61),D61,IF(AND(B61="T",R61="S"),D61,0))))) -> 0 | AD61: =IF(B61<>"E",0,IF(D61-C61<0,0,D61-C61)) -> 0
A62: =IF(ECIB!B35="","",ECIB!B35) | B62: =IF(ECIB!C35="","",ECIB!C35) | C62: =IF(INPUT!E44="","",INPUT!E44) | D62: =IF(INPUT!G44="","",INPUT!G44) | E62: =IF(ECIB!K35="","",ECIB!K35) | F62: =IF(ECIB!L35="","",ECIB!L35) | G62: =IF(H62="","",CONCATENATE(IF(ECIB!M35="","",ECIB!M35)," - ",TEXT(H62,"0,00"))) | H62: =IF(A62="","",IF(P62="y",ECIB!X35,O62)) | I62: =IFERROR(VLOOKUP(S62,Formulas!$T$2:$U$77,2,0),"") | J62: =IF(F62="",0,(F62-E62)/(365.25/12)) -> 0 | K62: =IF(E62="",0,(TODAY()-E62)/(365.25/12)) -> 0 | L62: =IF(AND(R62="U",NOT(E62="")),E62,"") | M62: =IF(AND(R62="S",NOT(E62="")),E62,"") | N62: =IF(AND(OR(A62=38,A62=54,A62=5,A62=8),R62="U"),C62,"") | O62: =IFERROR(IF(B62="E",(C62*0.05)+AD62,PMT(VLOOKUP(S62,Formulas!T:U,2,0)/12,J62,-C62)),0) -> 0 | P62: =ECIB!A35 | Q62: =IF(AND(OR(A62=38,A62=54,A62=5,A62=8),R62="S"),C62,"") | R62: =ECIB!M35 | S62: =A62&"-"&B62&"-"&R62 -> -- | AC62: =IF(AND(B62="E",R62="U",D62>C62),D62,IF(AND(B62="E",R62="U",D62<=C62),C62,IF(AND(B62="T",R62="U"),D62,IF(AND(B62="E",R62="S",D62>C62),D62,IF(AND(B62="T",R62="S"),D62,0))))) -> 0 | AD62: =IF(B62<>"E",0,IF(D62-C62<0,0,D62-C62)) -> 0
A63: =IF(ECIB!B40="","",ECIB!B40) | B63: =IF(ECIB!C40="","",ECIB!C40) | C63: =IF(INPUT!E45="","",INPUT!E45) | D63: =IF(INPUT!G45="","",INPUT!G45) | E63: =IF(ECIB!K40="","",ECIB!K40) | F63: =IF(ECIB!L40="","",ECIB!L40) | G63: =IF(H63="","",CONCATENATE(IF(ECIB!M40="","",ECIB!M40)," - ",TEXT(H63,"0,00"))) | H63: =IF(A63="","",IF(P63="y",ECIB!X40,O63)) | I63: =IFERROR(VLOOKUP(S63,Formulas!$T$2:$U$77,2,0),"") | J63: =IF(F63="",0,(F63-E63)/(365.25/12)) -> 0 | K63: =IF(E63="",0,(TODAY()-E63)/(365.25/12)) -> 0 | L63: =IF(AND(R63="U",NOT(E63="")),E63,"") | M63: =IF(AND(R63="S",NOT(E63="")),E63,"") | N63: =IF(AND(OR(A63=38,A63=54,A63=5,A63=8),R63="U"),C63,"") | O63: =IFERROR(IF(B63="E",(C63*0.05)+AD63,PMT(VLOOKUP(S63,Formulas!T:U,2,0)/12,J63,-C63)),0) -> 0 | P63: =ECIB!A40 | Q63: =IF(AND(OR(A63=38,A63=54,A63=5,A63=8),R63="S"),C63,"") | R63: =ECIB!M40 | S63: =A63&"-"&B63&"-"&R63 -> -- | AC63: =IF(AND(B63="E",R63="U",D63>C63),D63,IF(AND(B63="E",R63="U",D63<=C63),C63,IF(AND(B63="T",R63="U"),D63,IF(AND(B63="E",R63="S",D63>C63),D63,IF(AND(B63="T",R63="S"),D63,0))))) -> 0 | AD63: =IF(B63<>"E",0,IF(D63-C63<0,0,D63-C63)) -> 0
A64: =IF(ECIB!B41="","",ECIB!B41) | B64: =IF(ECIB!C41="","",ECIB!C41) | C64: =IF(INPUT!E46="","",INPUT!E46) | D64: =IF(INPUT!G46="","",INPUT!G46) | E64: =IF(ECIB!K41="","",ECIB!K41) | F64: =IF(ECIB!L41="","",ECIB!L41) | G64: =IF(H64="","",CONCATENATE(IF(ECIB!M41="","",ECIB!M41)," - ",TEXT(H64,"0,00"))) | H64: =IF(A64="","",IF(P64="y",ECIB!X41,O64)) | I64: =IFERROR(VLOOKUP(S64,Formulas!$T$2:$U$77,2,0),"") | J64: =IF(F64="",0,(F64-E64)/(365.25/12)) -> 0 | K64: =IF(E64="",0,(TODAY()-E64)/(365.25/12)) -> 0 | L64: =IF(AND(R64="U",NOT(E64="")),E64,"") | M64: =IF(AND(R64="S",NOT(E64="")),E64,"") | N64: =IF(AND(OR(A64=38,A64=54,A64=5,A64=8),R64="U"),C64,"") | O64: =IFERROR(IF(B64="E",(C64*0.05)+AD64,PMT(VLOOKUP(S64,Formulas!T:U,2,0)/12,J64,-C64)),0) -> 0 | P64: =ECIB!A41 | Q64: =IF(AND(OR(A64=38,A64=54,A64=5,A64=8),R64="S"),C64,"") | R64: =ECIB!M41 | S64: =A64&"-"&B64&"-"&R64 -> -- | AC64: =IF(AND(B64="E",R64="U",D64>C64),D64,IF(AND(B64="E",R64="U",D64<=C64),C64,IF(AND(B64="T",R64="U"),D64,IF(AND(B64="E",R64="S",D64>C64),D64,IF(AND(B64="T",R64="S"),D64,0))))) -> 0 | AD64: =IF(B64<>"E",0,IF(D64-C64<0,0,D64-C64)) -> 0
A65: =IF(ECIB!B42="","",ECIB!B42) | B65: =IF(ECIB!C42="","",ECIB!C42) | C65: =IF(INPUT!E47="","",INPUT!E47) | D65: =IF(INPUT!G47="","",INPUT!G47) | E65: =IF(ECIB!K42="","",ECIB!K42) | F65: =IF(ECIB!L42="","",ECIB!L42) | G65: =IF(H65="","",CONCATENATE(IF(ECIB!M42="","",ECIB!M42)," - ",TEXT(H65,"0,00"))) | H65: =IF(A65="","",IF(P65="y",ECIB!X42,O65)) | I65: =IFERROR(VLOOKUP(S65,Formulas!$T$2:$U$77,2,0),"") | J65: =IF(F65="",0,(F65-E65)/(365.25/12)) -> 0 | K65: =IF(E65="",0,(TODAY()-E65)/(365.25/12)) -> 0 | L65: =IF(AND(R65="U",NOT(E65="")),E65,"") | M65: =IF(AND(R65="S",NOT(E65="")),E65,"") | N65: =IF(AND(OR(A65=38,A65=54,A65=5,A65=8),R65="U"),C65,"") | O65: =IFERROR(IF(B65="E",(C65*0.05)+AD65,PMT(VLOOKUP(S65,Formulas!T:U,2,0)/12,J65,-C65)),0) -> 0 | P65: =ECIB!A42 | Q65: =IF(AND(OR(A65=38,A65=54,A65=5,A65=8),R65="S"),C65,"") | R65: =ECIB!M42 | S65: =A65&"-"&B65&"-"&R65 -> -- | AC65: =IF(AND(B65="E",R65="U",D65>C65),D65,IF(AND(B65="E",R65="U",D65<=C65),C65,IF(AND(B65="T",R65="U"),D65,IF(AND(B65="E",R65="S",D65>C65),D65,IF(AND(B65="T",R65="S"),D65,0))))) -> 0 | AD65: =IF(B65<>"E",0,IF(D65-C65<0,0,D65-C65)) -> 0
C66: =IF(INPUT!E48="","",INPUT!E48) | D66: =IF(INPUT!G48="","",INPUT!G48) | J66: =IF(F66="",0,(F66-E66)/(365.25/12)) -> 0 | K66: =IF(E66="",0,(TODAY()-E66)/(365.25/12)) -> 0
C67: =IF(INPUT!E49="","",INPUT!E49) | D67: =IF(INPUT!G49="","",INPUT!G49) | J67: =IF(F67="",0,(F67-E67)/(365.25/12)) -> 0 | K67: =IF(E67="",0,(TODAY()-E67)/(365.25/12)) -> 0
C68: =IF(INPUT!E50="","",INPUT!E50) | D68: =IF(INPUT!G50="","",INPUT!G50) | J68: =IF(F68="",0,(F68-E68)/(365.25/12)) -> 0 | K68: =IF(E68="",0,(TODAY()-E68)/(365.25/12)) -> 0
C69: =IF(INPUT!E51="","",INPUT!E51) | D69: =IF(INPUT!G51="","",INPUT!G51) | J69: =IF(F69="",0,(F69-E69)/(365.25/12)) -> 0 | K69: =IF(E69="",0,(TODAY()-E69)/(365.25/12)) -> 0
C70: =IF(INPUT!E52="","",INPUT!E52) | D70: =IF(INPUT!G52="","",INPUT!G52) | J70: =IF(F70="",0,(F70-E70)/(365.25/12)) -> 0 | K70: =IF(E70="",0,(TODAY()-E70)/(365.25/12)) -> 0
A71: Support Signer 1 Signature with Stamp: | F71: Credit Signer 2 Signature with Stamp:
A76: ______________________________ | F76: ______________________________

Sheet ECIB
AC101: Product | AD101: T/E | AE101: LIMIT | AF101: Position as of | AG101: Present Balance | AH101: Minimum Amount Due | AI101: 30+ | AJ101: 60+ | AK101: 90+ | AL101: Financing Date | AM101: Maturity Date | AN101: Sec / Un Sec

Sheet Formulas
B1: Segments | D1: SUB - Segments | F1: Deviation | I1: Prime | K1: MOB-1 | L1: MOB-2 | M1: NR | Q1: Product | R1: Term/Evergreen | S1: Unsec / Sec | T1: Key | U1: Rate | AA1: 10 | AB1: =VLOOKUP(AA1,$Z$2:$AA$14,2,0) -> 10
A2: 1 | B2: Category A | C2: 1 | D2: Permanent | E2: 1 | F2: L1 | H2: 1 | I2: Yes | K2: 0 | L2: 6 | M2: NTI | Q2: 6 | R2: T | S2: U | T2: =Q2&"-"&R2&"-"&S2 -> 6-T-U | U2: 0.1866 | Z2: 1 | AA2: 1
A3: =A2+1 -> 2 | B3: Category B | C3: =C2+1 -> 2 | D3: Contractual | E3: =E2+1 -> 2 | F3: L2 | H3: =H2+1 -> 2 | I3: No | K3: 7 | L3: 11 | M3: NTI | Q3: 26 | R3: T | S3: U | T3: =Q3&"-"&R3&"-"&S3 -> 26-T-U | U3: 0.29 | Z3: 2 | AA3: 2
A4: =A3+1 -> 3 | B4: Category C | C4: 3 | D4: Self Employed | E4: =E3+1 -> 3 | F4: L3 | I4: {=XLOOKUP(INPUT!H8, I2:I3, H2:H3, "")} | K4: 12 | L4: 1000 | M4: HBC | Q4: 38 | R4: T | S4: U | T4: =Q4&"-"&R4&"-"&S4 -> 38-T-U | U4: 0.2779 | Z4: 3 | AA4: 3
A5: =A4+1 -> 4 | B5: Non Approved Company | E5: =E4+1 -> 4 | F5: PR | I5: =VLOOKUP(I4,H2:I3,2,0) -> #N/A | Q5: 59 | R5: T | S5: U | T5: =Q5&"-"&R5&"-"&S5 -> 59-T-U | U5: 0.37 | Z5: 4 | AA5: 4
A6: =A5+1 -> 5 | B6: Self Employed | D6: {=XLOOKUP(INPUT!H6, D2:D4, C2:C4, "")} | E6: =E5+1 -> 5 | F6: No Deviation | Q6: 8 | R6: E | S6: U | T6: =Q6&"-"&R6&"-"&S6 -> 8-E-U | U6: 0.05 | Z6: 5 | AA6: 5
D7: =VLOOKUP(D6,$C$2:$D$4,2,0) -> #N/A | F7: {=XLOOKUP(INPUT!H7, F2:F6, E2:E6, "")} | I7: =IF(I5="Yes",6,IF(AND(B9="Self Employed",C13="NTI",E11<=99999),1,IF(AND(B9="Self Employed",C13="HBC",E11<=99999),2,IF(AND(B9="Self Employed",C13="NTI",E11>=100000),2,IF(AND(B9="Self Employed",C13="HBC",E11>=100000),3,IF(AND(D30="EB",C13="NTI",E11<=100000),1.5,IF(AND(D30="EB",C13="HBC",E11<=100000),2,IF(AND(D30="EB",C13="NTI",E11<200000),2,IF(AND(D30="EB",C13="HBC",E11<200000),3,IF(AND(D30="EB",C13="NTI",E11>=200000),4,IF(AND(D30="EB",C13="HBC",E11>=200000),5,IF(AND(B10="LTM",C13="NTI"),LOOKUP(E11,$H$9:$I$12,$J$9:$J$12),IF(AND(B10="LTM",C13="HBC"),LOOKUP(E11,$H$9:$I$12,K9:K12),IF(AND(B10="STM",C13="NTI"),LOOKUP(E11,$H$9:$I$12,$L$9:$L$12),IF(AND(B10="STM",C13="HBC"),LOOKUP(E11,$H$9:$I$12,$M$9:$M$12)))))))))))))))) -> #N/A | J7: LTM | L7: STM | N7: Self Employed | Q7: 34 | R7: E | S7: U | T7: =Q7&"-"&R7&"-"&S7 -> 34-E-U | U7: 0.2779 | Z7: 6 | AA7: 6
B8: {=XLOOKUP(INPUT!H5, B2:B6, A2:A6, "")} | F8: =VLOOKUP(F7,$E$2:$F$6,2,0) -> #N/A | H8: Mutiples | J8: NTI | K8: HBC | L8: NTI | M8: HBC | N8: NTI | O8: HBC | Q8: 38 | R8: E | S8: U | T8: =Q8&"-"&R8&"-"&S8 -> 38-E-U | U8: 0.2779 | Z8: 7 | AA8: 7
B9: =VLOOKUP(B8,$A$2:$B$6,2,0) -> #N/A | C9: =VLOOKUP(B9,I16:J20,2,0) -> #N/A | D9: =IF(AND(B8=5,D6<4),"Wrong Emp. Cat Selected",IF(AND(B8<5,D6=4),"Wrong Emp. Cat Selected","")) | H9: 1 | I9: 70000 | J9: =IF(D7="Permanent",2,1.5) -> #N/A | K9: =IF(D7="Permanent",3,2) -> #N/A | L9: =IF(D7="Permanent",1.5,1) -> #N/A | M9: =IF(D7="Permanent",2,1.5) -> #N/A | N9: 1 | O9: =IF(D7="Permanent",2,0) -> #N/A | Q9: 54 | R9: E | S9: U | T9: =Q9&"-"&R9&"-"&S9 -> 54-E-U | U9: 0.2779 | Z9: 8 | AA9: 8
B10: =IF(B8<=2,"LTM","STM") -> STM | E10: Income | H10: 70001 | I10: 100000 | J10: =IF(D7="Permanent",3,2) -> #N/A | K10: =IF(D7="Permanent",4,3) -> #N/A | L10: =IF(D7="Permanent",1.5,1) -> #N/A | M10: =IF(D7="Permanent",2,1.5) -> #N/A | N10: 1 | O10: =IF(D7="Permanent",2,0) -> #N/A | Q10: 1 | R10: T | S10: S | T10: =Q10&"-"&R10&"-"&S10 -> 1-T-S | U10: 0.28 | Z10: 9 | AA10: 9
E11: =INPUT!M5 | H11: 100001 | I11: 9999999 | J11: =IF(D7="Permanent",3,2) -> #N/A | K11: =IF(D7="Permanent",4,3) -> #N/A | L11: =IF(D7="Permanent",2.5,2) -> #N/A | M11: =IF(D7="Permanent",3,2.5) -> #N/A | N11: 1 | O11: =IF(D7="Permanent",3,3) -> #N/A | Q11: 2 | R11: T | S11: S | T11: =Q11&"-"&R11&"-"&S11 -> 2-T-S | U11: 0.28 | Z11: 10 | AA11: 10
B12: Bureau | D12: PRIME | E12: =IF(AND(I5="Yes",E11<400000),"Below Income","") -> #N/A | H12: 200000 | I12: 1000000 | J12: =IF(D7="Permanent",3,2) -> #N/A | K12: =IF(D7="Permanent",4,3) -> #N/A | L12: =IF(D7="Permanent",2.5,2) -> #N/A | M12: =IF(D7="Permanent",3,2.5) -> #N/A | N12: 1 | O12: =IF(D7="Permanent",3,3) -> #N/A | Q12: 4 | R12: T | S12: S | T12: =Q12&"-"&R12&"-"&S12 -> 4-T-S | U12: 0.1866 | Z12: 11 | AA12: 11
B13: =MAX('DBR Sheet'!$K$34:$K$65) -> 0 | C13: =LOOKUP($B$13,$K$2:$L$4,$M$2:$M$4) -> NTI | D13: EB | E13: =IF(AND(D30="EB",E11<=29999),"Below Income","") -> #N/A | Q13: 5 | R13: T | S13: S | T13: =Q13&"-"&R13&"-"&S13 -> 5-T-S | U13: 0.2779 | Z13: 12 | AA13: 12
D14: others | E14: =IF(AND(B8=1,C9="Salaried",E11<=39999),"Below Income",IF(AND(B8=2,C9="Salaried",E11<=39999),"Below Income",IF(AND(B8=3,C9="Salaried",E11<=69999),"Below Income",IF(AND(B8=4,C9="Salaried",E11<=69999),"Below Income",IF(AND(C9="SEB",C13="NTI",E11<=59999),"Below Income",IF(AND(C9="SEB",C13="HBC",E11<=59999),"Below Income","")))))) -> #N/A | Q14: 9 | R14: T | S14: S | T14: =Q14&"-"&R14&"-"&S14 -> 9-T-S | U14: 0.1866 | Z14: 13 | AA14: NA
E15: =IF(I5="Yes",E12,IF(D30="EB",E13,E14)) -> #N/A | Q15: 17 | R15: T | S15: S | T15: =Q15&"-"&R15&"-"&S15 -> 17-T-S | U15: 0.26
B16: Ascore | I16: Category A | J16: Salaried | Q16: 21 | R16: T | S16: S | T16: =Q16&"-"&R16&"-"&S16 -> 21-T-S | U16: 0.27
B17: Company Type | C17: =IF(D17="Salaried",A_Score!$G$4,A_Score!$N$4) -> #N/A | D17: =IF(B9="Self Employed","Self Employed","Salaried") -> #N/A | I17: Category B | J17: Salaried | Q17: 25 | R17: T | S17: S | T17: =Q17&"-"&R17&"-"&S17 -> 25-T-S | U17: 0.27
B18: STM / LTM | C18: 75 | D18: =B10 -> STM | I18: Category C | J18: Salaried | Q18: 29 | R18: T | S18: S | T18: =Q18&"-"&R18&"-"&S18 -> 29-T-S | U18: 0.1906
B19: Age | C19: =IF(D17="Salaried",LOOKUP(D19,A_Score!$B$28:$C$33,A_Score!$G$28:$G$33),LOOKUP(D19,A_Score!$I$28:$J$33,A_Score!$N$28:$N$33)) -> #N/A | D19: =INPUT!C9 | I19: Non Approved Company | J19: Salaried | Q19: 30 | R19: T | S19: S | T19: =Q19&"-"&R19&"-"&S19 -> 30-T-S | U19: 0.24
B20: Income | C20: =IF(D17="Salaried",LOOKUP(D20,A_Score!$B$14:$C$18,A_Score!$G$14:$G$18),LOOKUP(D20,A_Score!$I$15:$J$19,A_Score!$N$15:$N$19)) -> #N/A | D20: =INPUT!M5 | I20: Self Employed | J20: SEB | Q20: 31 | R20: T | S20: S | T20: =Q20&"-"&R20&"-"&S20 -> 31-T-S | U20: 0.24
B21: DBR | C21: =IF(D17="Salaried",LOOKUP(D21,A_Score!$B$22:$C$25,A_Score!$G$22:$G$25),LOOKUP(D21,A_Score!$I$22:$J$25,A_Score!$N$22:$N$25)) -> #N/A | D21: ='DBR Sheet'!B28 -> #DIV/0! | I21: Employee Banking | J21: EB | Q21: 33 | R21: T | S21: S | T21: =Q21&"-"&R21&"-"&S21 -> 33-T-S | U21: 0.24
B22: Bureau | C22: =IF(D17="Salaried",VLOOKUP(D22,A_Score!$D$11:$G$12,4,0),VLOOKUP(D22,A_Score!K11:N12,4,0)) -> #N/A | D22: =IF(C13="HBC","ESB","NTB") -> NTB | Q22: 35 | R22: T | S22: S | T22: =Q22&"-"&R22&"-"&S22 -> 35-T-S | U22: 0.19
B23: Deviation | C23: =IF(AND(F7<5,D17="Salaried"),329,IF(AND(F7<5,D17="Self Employed"),259,"")) -> #N/A | D23: =F8 -> #N/A | L23: ='DBR Sheet'!F6 -> 0 | M23: Total EMI | Q23: 37 | R23: T | S23: S | T23: =Q23&"-"&R23&"-"&S23 -> 37-T-S | U23: 0.37
C24: =MIN(SUM(C17:C22),C23) -> #N/A | I24: Limit As per Multiples | J24: =E11*I7 -> #N/A | L24: =O24*0.45 -> 0 | M24: NET income * 45% | O24: =INPUT!M10 | Q24: 57 | R24: T | S24: S | T24: =Q24&"-"&R24&"-"&S24 -> 57-T-S | U24: 0.37
I25: Limit As per DBR | J25: =L26 -> 0 | L25: =L24-L23 -> 0 | Q25: 61 | R25: T | S25: S | T25: =Q25&"-"&R25&"-"&S25 -> 61-T-S | U25: 0.1866
C26: EB | I26: As per Uns Exposure | J26: ='DBR Sheet'!F13 -> #N/A | L26: =L25*100/5 -> 0 | Q26: 62 | R26: T | S26: S | T26: =Q26&"-"&R26&"-"&S26 -> 62-T-S | U26: 0.1906
B27: 1 | C27: Yes | I27: Unsec Max Limit | J27: =IF(I5="Yes",7000000*0.95,3000000*0.95) -> #N/A | Q27: 16 | R27: T | S27: S | T27: =Q27&"-"&R27&"-"&S27 -> 16-T-S | U27: 0.26
B28: =B27+1 -> 2 | C28: No | I28: Allowable Limit As Per Policy | J28: =IF(MIN(J24:J27)<0,0,MIN(J24:J27)) -> #N/A | Q28: 8 | R28: E | S28: S | T28: =Q28&"-"&R28&"-"&S28 -> 8-E-S | U28: 0.05
C29: {=XLOOKUP(INPUT!K5, C27:C28, B27:B28, "")} | Q29: 34 | R29: E | S29: S | T29: =Q29&"-"&R29&"-"&S29 -> 34-E-S | U29: 0.2779
C30: =VLOOKUP(C29,B27:C28,2,0) -> #N/A | D30: =IF(C30="Yes","EB","") -> #N/A | Q30: 38 | R30: E | S30: S | T30: =Q30&"-"&R30&"-"&S30 -> 38-E-S | U30: 0.2779
Q31: 54 | R31: E | S31: S | T31: =Q31&"-"&R31&"-"&S31 -> 54-E-S | U31: 0.2779
Q32: 1 | R32: E | S32: U | T32: =Q32&"-"&R32&"-"&S32 -> 1-E-U | U32: 0.28
Q33: 3 | R33: T | S33: S | T33: =Q33&"-"&R33&"-"&S33 -> 3-T-S | U33: 0.28
Q34: 5 | R34: E | S34: U | T34: =Q34&"-"&R34&"-"&S34 -> 5-E-U | U34: 0.2779
Q35: 6 | R35: T | S35: S | T35: =Q35&"-"&R35&"-"&S35 -> 6-T-S | U35: 0.1866
Q36: 7 | R36: E | S36: U | T36: =Q36&"-"&R36&"-"&S36 -> 7-E-U | U36: 0.05
Q37: 10 | R37: T | S37: S | T37: =Q37&"-"&R37&"-"&S37 -> 10-T-S | U37: 0.24
Q38: 11 | R38: T | S38: S | T38: =Q38&"-"&R38&"-"&S38 -> 11-T-S | U38: 0.24
Q39: 12 | R39: T | S39: S | T39: =Q39&"-"&R39&"-"&S39 -> 12-T-S | U39: 0.24
Q40: 13 | R40: T | S40: S | T40: =Q40&"-"&R40&"-"&S40 -> 13-T-S | U40: 0.24
Q41: 14 | R41: T | S41: S | T41: =Q41&"-"&R41&"-"&S41 -> 14-T-S | U41: 0.24
Q42: 15 | R42: T | S42: S | T42: =Q42&"-"&R42&"-"&S42 -> 15-T-S | U42: 0.26
... Q77: 65 | R77: T | S77: S | T77: =Q77&"-"&R77&"-"&S77 -> 65-T-S | U77: 0.28

Sheet A_Score
E1: Salaried | L1: Self | R1: =Formulas!D17 -> #N/A | Y1: Salaried | Z1: Self
R2: =Formulas!C24 -> #N/A | U2: U | Y2: =IF(AND(R3="No Deviation",R1="Salaried"),LOOKUP(R2,$Q$10:$R$16,$S$10:$S$16),IF(R3<>"No Deviation",VLOOKUP(R3,$U$3:$V$5,2,0),"")) -> #N/A | Z2: =IF(AND(R3="No Deviation",R1<>"Salaried"),LOOKUP(R2,$U$10:$V$16,$W$10:$W$16),IF(R3<>"No Deviation",VLOOKUP(R3,$U$3:$V$5,2,0),"")) -> #N/A
E3: Weight | F3: Score | G3: Net | L3: Weight | M3: Score | N3: Net | R3: =Formulas!D23 -> #N/A | U3: L1 | V3: 8
D4: Salaried | E4: 0.15 | F4: 100 | G4: =F4 -> 100 | K4: Self | L4: 0.15 | M4: 40 | N4: =M4 -> 40 | Q4: Rating _A | R4: =IF(R1="Salaried",Y2,Z2) -> #N/A | U4: L2 | V4: 7
G5: 15 | Q5: Rating _B | R5: =IF(Formulas!AB1="NA",A_Score!R4,Formulas!AB1) -> 10 | U5: L3 | V5: 9
D6: Company Cat | K6: Company Cat
D7: LTM | E7: 0.15 | F7: 100 | G7: =F7 -> 100 | K7: LTM
D8: STM | E8: 0.15 | F8: 75 | G8: =F8 -> 75 | K8: STM | Q8: Salaried | U8: Self Employed
G9: =MAX(G7:G8) -> 100 | Q9: Score Band | S9: ORR | U9: Score Band | W9: ORR
D10: Bureau | K10: Bureau | Q10: 0 | R10: 329 | S10: 7/8/9 | U10: 0 | V10: 259 | W10: 7/8/9
D11: NTB | E11: 0.2 | F11: 40 | G11: =F11 -> 40 | K11: NTB | L11: 0.25 | M11: 40 | N11: =M11 -> 40 | Q11: =R10+1 -> 330 | R11: 400 | S11: 6 | U11: =V10+1 -> 260 | V11: 400 | W11: 6
D12: ESB | E12: 0.2 | F12: 100 | G12: =F12 -> 100 | K12: ESB | L12: 0.25 | M12: 100 | N12: =M12 -> 100 | Q12: =R11+1 -> 401 | R12: =R11+60 -> 460 | S12: 5 | U12: =V11+1 -> 401 | V12: =V11+60 -> 460 | W12: 5
G13: =MAX(G11:G12) -> 100 | Q13: =R12+1 -> 461 | R13: =R12+65 -> 525 | S13: 4 | U13: =V12+1 -> 461 | V13: =V12+65 -> 525 | W13: 4
D14: Income | K14: Income | Q14: =R13+1 -> 526 | R14: =R13+65 -> 590 | S14: 3 | U14: =V13+1 -> 526 | V14: =V13+65 -> 590 | W14: 3
B15: 0 | C15: 19999 | D15: <20k | E15: 0 | F15: 0 | G15: 0 | I15: 0 | J15: 39999 | K15: <40k | L15: 0 | M15: 0 | N15: =M15 -> 0 | Q15: =R14+1 -> 591 | R15: =R14+50 -> 640 | S15: 2 | U15: =V14+1 -> 591 | V15: =V14+50 -> 640 | W15: 2
B16: =C15+1 -> 20000 | C16: 50000 | D16: >20k- 50k | E16: 0.2 | F16: 40 | G16: =F16 -> 40 | I16: 40000 | J16: 65000 | K16: >40k- 65k | L16: 0.2 | M16: 30 | N16: =M16 -> 30 | Q16: =R15+1 -> 641 | R16: 700000 | S16: 1 | U16: =V15+1 -> 641 | V16: 700000 | W16: 1
B17: =C16+1 -> 50001 | C17: 100000 | D17: >50k- 100k | E17: 0.2 | F17: 75 | G17: =F17 -> 75 | I17: 65001 | J17: 100000 | K17: >65k- 100k | L17: 0.2 | M17: 60 | N17: =M17 -> 60
B18: =C17+1 -> 100001 | C18: 9000000000 | D18: >100k | E18: 0.2 | F18: 100 | G18: =F18 -> 100 | I18: 100001 | J18: 200000 | K18: 100k- 200k | L18: 0.2 | M18: 75 | N18: =M18 -> 75
G19: =MAX(G15:G18) -> 100 | I19: 200001 | J19: 9000000000 | K19: >200k | L19: 0.2 | M19: 100 | N19: =M19 -> 100
D21: Debt Burden | K21: Debt Burden
B22: 0 | C22: 0.2 | D22: <20% | E22: 0.2 | F22: 100 | G22: =F22 -> 100 | I22: 0 | J22: 0.2 | K22: <20% | L22: 0.25 | M22: 100 | N22: =M22 -> 100
B23: 0.2001 | C23: 0.3 | D23: >20% - 30% | E23: 0.2 | F23: 75 | G23: =F23 -> 75 | I23: 0.2001 | J23: 0.3 | K23: >20% - 30% | L23: 0.25 | M23: 75 | N23: =M23 -> 75
B24: 0.3001 | C24: 0.4 | D24: >30% - 40% | E24: 0.2 | F24: 60 | G24: =F24 -> 60 | I24: 0.3001 | J24: 0.4 | K24: >30% - 40% | L24: 0.25 | M24: 60 | N24: =M24 -> 60
B25: 0.4001 | C25: 100 | D25: >40% - 50% | E25: 0.2 | F25: 40 | G25: =F25 -> 40 | I25: 0.4001 | J25: 100 | K25: >40% - 50% | L25: 0.25 | M25: 40 | N25: =M25 -> 40
G26: =MAX(G22:G25) -> 100
D27: Age | K27: Age
B28: 0 | C28: 17.99 | D28: <18 | E28: 0 | F28: 0 | G28: =F28 -> 0 | I28: 0 | J28: 17.99 | K28: <18 | L28: 0 | M28: 0 | N28: =M28 -> 0
B29: 18.01 | C29: 25 | D29: >18 - 25 | E29: 0.1 | F29: 30 | G29: =F29 -> 30 | I29: 18.01 | J29: 25 | K29: >18 - 25 | L29: 0.15 | M29: 30 | N29: =M29 -> 30
B30: 25.01 | C30: 30 | D30: >25 - 30 | E30: 0.1 | F30: 40 | G30: =F30 -> 40 | I30: 25.01 | J30: 30 | K30: >25 - 30 | L30: 0.15 | M30: 40 | N30: =M30 -> 40
B31: 30.01 | C31: 40 | D31: >30 - 40 | E31: 0.1 | F31: 60 | G31: =F31 -> 60 | I31: 30.01 | J31: 40 | K31: >30 - 40 | L31: 0.15 | M31: 60 | N31: =M31 -> 60
B32: 40.01 | C32: 50 | D32: >40 - 50 | E32: 0.1 | F32: 100 | G32: =F32 -> 100 | I32: 40.01 | J32: 50 | K32: >40 - 50 | L32: 0.15 | M32: 100 | N32: =M32 -> 100
B33: 50.01 | C33: 700000 | D33: >50 - 70 | E33: 0.1 | F33: 75 | G33: =F33 -> 75 | I33: 50.01 | J33: 700000 | K33: >50 - 70 | L33: 0.15 | M33: 75 | N33: =M33 -> 75
G34: =MAX(G28:G33) -> 100
